adder/adder_out.sv
/* Generated by Yosys 0.36+3 (git sha1 a53032104, aarch64-apple-darwin20.2-clang 10.0.0-4ubuntu1 -fPIC -Os) */

(* top =  1  *)
(* src = "adder.sv:3.1-18.10" *)
module adder(a_in, b_in, x_out, clk, scan_in, scan_en, scan_out);
  (* src = "adder.sv:11.5-16.8" *)
  wire _00_;
  (* src = "adder.sv:11.5-16.8" *)
  wire _01_;
  (* src = "adder.sv:11.5-16.8" *)
  wire _02_;
  (* src = "adder.sv:11.5-16.8" *)
  wire _03_;
  (* src = "adder.sv:11.5-16.8" *)
  wire _04_;
  wire _05_;
  wire _06_;
  wire _07_;
  wire _08_;
  wire _09_;
  wire _10_;
  wire _11_;
  wire _12_;
  wire _13_;
  wire _14_;
  wire _15_;
  wire _16_;
  wire _17_;
  (* src = "adder.sv:4.23-4.27" *)
  input [3:0] a_in;
  wire [3:0] a_in;
  (* src = "adder.sv:9.17-9.22" *)
  reg \a_reg[0] ;
  (* src = "adder.sv:9.17-9.22" *)
  reg \a_reg[1] ;
  (* src = "adder.sv:9.17-9.22" *)
  reg \a_reg[2] ;
  (* src = "adder.sv:9.17-9.22" *)
  reg \a_reg[3] ;
  (* src = "adder.sv:4.29-4.33" *)
  input [3:0] b_in;
  wire [3:0] b_in;
  (* src = "adder.sv:9.24-9.29" *)
  reg \b_reg[0] ;
  (* src = "adder.sv:9.24-9.29" *)
  reg \b_reg[1] ;
  (* src = "adder.sv:9.24-9.29" *)
  reg \b_reg[2] ;
  (* src = "adder.sv:9.24-9.29" *)
  wire \b_reg[3] ;
  (* src = "adder.sv:6.17-6.20" *)
  input clk;
  wire clk;
  input scan_en;
  wire scan_en;
  input scan_in;
  wire scan_in;
  output scan_out;
  reg scan_out;
  (* src = "adder.sv:5.24-5.29" *)
  output [4:0] x_out;
  reg [4:0] x_out;
  assign { _04_, _03_, _02_, _01_, _00_ } = { \a_reg[3] , \a_reg[2] , \a_reg[1] , \a_reg[0]  } + (* src = "adder.sv:15.18-15.31" *) { scan_out, \b_reg[2] , \b_reg[1] , \b_reg[0]  };
  (* \always_ff  = 32'd1 *)
  (* src = "adder.sv:11.5-16.8" *)
  always @(posedge clk)
    x_out <= { _17_, _06_, _07_, _08_, _09_ };
  (* \always_ff  = 32'd1 *)
  (* src = "adder.sv:11.5-16.8" *)
  always @(posedge clk)
    \a_reg[0]  <= _16_;
  (* \always_ff  = 32'd1 *)
  (* src = "adder.sv:11.5-16.8" *)
  always @(posedge clk)
    \a_reg[1]  <= _15_;
  (* \always_ff  = 32'd1 *)
  (* src = "adder.sv:11.5-16.8" *)
  always @(posedge clk)
    \a_reg[2]  <= _14_;
  (* \always_ff  = 32'd1 *)
  (* src = "adder.sv:11.5-16.8" *)
  always @(posedge clk)
    \a_reg[3]  <= _13_;
  (* \always_ff  = 32'd1 *)
  (* src = "adder.sv:11.5-16.8" *)
  always @(posedge clk)
    \b_reg[0]  <= _12_;
  (* \always_ff  = 32'd1 *)
  (* src = "adder.sv:11.5-16.8" *)
  always @(posedge clk)
    \b_reg[1]  <= _11_;
  (* \always_ff  = 32'd1 *)
  (* src = "adder.sv:11.5-16.8" *)
  always @(posedge clk)
    \b_reg[2]  <= _10_;
  (* \always_ff  = 32'd1 *)
  (* src = "adder.sv:11.5-16.8" *)
  always @(posedge clk)
    scan_out <= _05_;
  assign _09_ = scan_en ? scan_in : _00_;
  assign _08_ = scan_en ? x_out[0] : _01_;
  assign _07_ = scan_en ? x_out[1] : _02_;
  assign _06_ = scan_en ? x_out[2] : _03_;
  assign _17_ = scan_en ? x_out[3] : _04_;
  assign _16_ = scan_en ? x_out[4] : a_in[0];
  assign _15_ = scan_en ? \a_reg[0]  : a_in[1];
  assign _14_ = scan_en ? \a_reg[1]  : a_in[2];
  assign _13_ = scan_en ? \a_reg[2]  : a_in[3];
  assign _12_ = scan_en ? \a_reg[3]  : b_in[0];
  assign _11_ = scan_en ? \b_reg[0]  : b_in[1];
  assign _10_ = scan_en ? \b_reg[1]  : b_in[2];
  assign _05_ = scan_en ? \b_reg[2]  : b_in[3];
  assign \b_reg[3]  = scan_out;
endmodule

dump.vcd
$version Generated by VerilatedVcd $end
$timescale 1ps $end
 $scope module $rootio $end
  $var wire 4 # a_in [3:0] $end
  $var wire 4 $ b_in [3:0] $end
  $var wire 1 % clk $end
  $var wire 1 & scan_en $end
  $var wire 1 ' scan_in $end
  $var wire 1 ( scan_out $end
  $var wire 5 ) x_out [4:0] $end
 $upscope $end
 $scope module adder $end
  $var wire 4 * a_in [3:0] $end
  $var wire 1 + a_reg[0] $end
  $var wire 1 , a_reg[1] $end
  $var wire 1 - a_reg[2] $end
  $var wire 1 . a_reg[3] $end
  $var wire 4 / b_in [3:0] $end
  $var wire 1 0 b_reg[0] $end
  $var wire 1 1 b_reg[1] $end
  $var wire 1 2 b_reg[2] $end
  $var wire 1 3 b_reg[3] $end
  $var wire 1 4 clk $end
  $var wire 1 5 scan_en $end
  $var wire 1 6 scan_in $end
  $var wire 1 7 scan_out $end
  $var wire 5 8 x_out [4:0] $end
 $upscope $end
$enddefinitions $end


#0
b0000 #
b0000 $
1%
1&
0'
0(
b00000 )
b0000 *
0+
0,
0-
0.
b0000 /
00
01
02
03
14
15
06
07
b00000 8
#10000
0%
04
#20000
1%
1'
b00001 )
14
16
b00001 8
#30000
0%
04
#40000
1%
0'
b00010 )
14
06
b00010 8
#50000
0%
04
#60000
1%
1'
b00101 )
14
16
b00101 8
#70000
0%
04
#80000
1%
b01011 )
14
b01011 8
#90000
0%
04
#100000
1%
b10111 )
14
b10111 8
#110000
0%
04
#120000
1%
b01111 )
1+
14
b01111 8
#130000
0%
04
#140000
1%
b11111 )
0+
1,
14
b11111 8
#150000
0%
04
#160000
1%
0'
b11110 )
1+
0,
1-
14
06
b11110 8
#170000
0%
04
#180000
1%
b11100 )
1,
0-
1.
14
b11100 8
#190000
0%
04
#200000
1%
b11000 )
1-
0.
10
14
b11000 8
#210000
0%
04
#220000
1%
b10000 )
1.
00
11
14
b10000 8
#230000
0%
04
#240000
1%
b00000 )
10
01
12
14
b00000 8
#250000
0%
04
#260000
1%
0&
b10100 )
0+
0,
0-
0.
00
02
14
05
b10100 8
#270000
0%
04
#280000
1%
1&
b01000 )
1+
14
15
b01000 8
#290000
0%
04
#300000
1%
b10000 )
0+
1,
14
b10000 8
#310000
0%
04
#320000
1%
b00000 )
1+
0,
1-
14
b00000 8
#330000
0%
04
#340000
1%
0+
1,
0-
1.
14
#350000
0%
04
#360000
1%
0,
1-
0.
10
14
#370000
0%
04
#380000
1%
0-
1.
00
11
14
#390000
0%
04
#400000
1%
0.
10
01
12
14
#410000
0%
04
#420000
1%
1(
00
11
02
13
14
17
#430000
0%
04
#440000
1%
0(
01
12
03
14
07
#450000
0%
04
#460000
1%
1(
02
13
14
17
#470000
0%
04
#480000
1%
0(
03
14
07
